{
  "total_features": 115,
  "engineered_features": [
    "applicant_age_35-44",
    "applicant_age_45-54",
    "applicant_age_55-64",
    "applicant_age_65-74",
    "applicant_age_<25",
    "applicant_age_>74",
    "applicant_age_Not applicable",
    "applicant_age_above_62",
    "applicant_age_numeric",
    "combined_risk_score",
    "county_code_hashed",
    "county_frequency",
    "dti_hashed",
    "dti_ltv_interaction",
    "dti_risk_flag_High Risk",
    "dti_risk_flag_Low Risk",
    "dti_risk_flag_Moderate Risk",
    "dti_risk_flag_Unknown",
    "has_coborrower",
    "housing_expense_ratio",
    "income_bracket_$100-150K",
    "income_bracket_$150-250K",
    "income_bracket_$50-75K",
    "income_bracket_$75-100K",
    "income_bracket_>$250K",
    "income_coborrower_interaction",
    "loan_costs_ratio",
    "loan_rate_interaction",
    "loan_size_category_$200-300K",
    "loan_size_category_$300-400K",
    "loan_size_category_$400-600K",
    "loan_size_category_>$600K",
    "loan_to_income_ratio",
    "loan_to_value_ratio",
    "ltv_risk_flag_High Risk",
    "ltv_risk_flag_Low Risk",
    "ltv_risk_flag_Moderate Risk",
    "state_approval_rate",
    "state_code_hashed"
  ],
  "original_features": [
    "income",
    "loan_amount",
    "property_value",
    "interest_rate",
    "loan_term",
    "total_loan_costs",
    "applicant_age",
    "debt_to_income_ratio",
    "state_code",
    "county_code"
  ],
  "protected_features": [
    "derived_ethnicity",
    "derived_race",
    "derived_sex",
    "applicant_ethnicity_1",
    "co_applicant_ethnicity_1",
    "applicant_ethnicity_observed",
    "co_applicant_ethnicity_observed",
    "applicant_race_1",
    "co_applicant_race_1",
    "applicant_race_observed",
    "co_applicant_race_observed",
    "applicant_sex",
    "co_applicant_sex",
    "applicant_sex_observed",
    "co_applicant_sex_observed",
    "tract_minority_population_percent",
    "race_minority",
    "hispanic"
  ],
  "high_cardinality_features": [
    "county_code",
    "debt_to_income_ratio",
    "state_code"
  ],
  "modeling_features": [
    "unnamed:_0",
    "derived_msa_md",
    "census_tract",
    "lien_status",
    "total_units",
    "conforming_loan_limit",
    "purchaser_type",
    "preapproval",
    "reverse_mortgage",
    "open_end_line_of_credit",
    "business_or_commercial_purpose",
    "loan_amount",
    "combined_loan_to_value_ratio",
    "interest_rate",
    "rate_spread",
    "hoepa_status",
    "total_loan_costs",
    "total_points_and_fees",
    "origination_charges",
    "discount_points",
    "lender_credits",
    "loan_term",
    "prepayment_penalty_term",
    "intro_rate_period",
    "negative_amortization",
    "interest_only_payment",
    "balloon_payment",
    "other_nonamortizing_features",
    "property_value",
    "manufactured_home_secured_property_type",
    "manufactured_home_land_property_interest",
    "income",
    "applicant_credit_score_type",
    "co_applicant_credit_score_type",
    "co_applicant_age",
    "applicant_age_above_62",
    "submission_of_application",
    "initially_payable_to_institution",
    "aus_1",
    "denial_reason_1",
    "tract_population",
    "ffiec_msa_md_median_family_income",
    "tract_to_msa_income_percentage",
    "tract_owner_occupied_units",
    "tract_one_to_four_family_homes",
    "tract_median_age_of_housing_units",
    "loan_type_Federal Housing Administration insured (FHA)",
    "loan_type_USDA Rural Housing Service or Farm Service Agency guaranteed (RHS or FSA)",
    "loan_type_Veterans Affairs guaranteed (VA)",
    "construction_method_Site-Built",
    "has_coborrower",
    "loan_to_income_ratio",
    "loan_to_value_ratio",
    "housing_expense_ratio",
    "loan_costs_ratio",
    "combined_risk_score",
    "application_type",
    "state_approval_rate",
    "county_frequency",
    "dti_ltv_interaction",
    "income_coborrower_interaction",
    "loan_rate_interaction",
    "applicant_age_numeric",
    "age_income_interaction",
    "loan_size_category_$200-300K",
    "loan_size_category_$300-400K",
    "loan_size_category_$400-600K",
    "loan_size_category_>$600K",
    "income_bracket_$50-75K",
    "income_bracket_$75-100K",
    "income_bracket_$100-150K",
    "income_bracket_$150-250K",
    "income_bracket_>$250K",
    "ltv_risk_flag_High Risk",
    "ltv_risk_flag_Low Risk",
    "ltv_risk_flag_Moderate Risk",
    "dti_risk_flag_High Risk",
    "dti_risk_flag_Low Risk",
    "dti_risk_flag_Moderate Risk",
    "dti_risk_flag_Unknown",
    "applicant_age_35-44",
    "applicant_age_45-54",
    "applicant_age_55-64",
    "applicant_age_65-74",
    "applicant_age_<25",
    "applicant_age_>74",
    "applicant_age_Not applicable",
    "state_code_hashed",
    "dti_hashed",
    "county_code_hashed"
  ]
}